{
  "sprites": [
    {
      "fileName": "img_1088.png",
      "width": 1080,
      "height": 1920,
      "x": 0,
      "y": 0
    },
    {
      "fileName": "img_1089.png",
      "width": 1080,
      "height": 1920,
      "x": 1080,
      "y": 0
    },
    {
      "fileName": "img_1090.png",
      "width": 1080,
      "height": 1920,
      "x": 2160,
      "y": 0
    },
    {
      "fileName": "img_1091.png",
      "width": 1080,
      "height": 1920,
      "x": 3240,
      "y": 0
    },
    {
      "fileName": "img_1092.png",
      "width": 1080,
      "height": 1920,
      "x": 4320,
      "y": 0
    }
  ],
  "packMode": "horizontal",
  "padding": 0,
  "backgroundColor": "rgba(0, 0, 0, 0)",
  "spriteSheetWidth": 5400,
  "spriteSheetHeight": 1920
}